{"Title": "04/24/2014 Merchtem, Flanders, Belgium", "Acitvity Type": "Ride", "Date": "April 24, 2014", "Time": "11:05 AM on Thursday", "Basic Stats": {"Distance": "51.45km", "Moving Time": "1:55:21", "Elevation": "153m"}, "Secondary Stats": {"Estimated Avg Power": "118W", "Energy Output": "817kJ"}, "More Stats": {"Speed": {"Avg": "26.8km/h", "Max": "50.4km/h"}, "Calories": {"Avg": "911", "Max": null}, "Temperature": {"Avg": "13\u2103", "Max": null}, "Elapsed Time": {"Avg": "8:58:23", "Max": null}}}